{
  "id": "ens-domains",
  "previewType": "card",
  "sampleResponse": {
    "name": "vitalik.eth",
    "address": "0xd8dA6BF26964aF9D7eEd9e03E53415D37aA96045",
    "registrant": "0xd8dA6BF26964aF9D7eEd9e03E53415D37aA96045",
    "expiry_date": "2032-05-04T09:00:00Z",
    "resolver": "0x4976fb03C32e5B8cfe2b6cCB31c09Ba78EBaBa41",
    "content_hash": "ipfs://QmRAQB6YaCyidP37UdDnjFY5vQuiBrcqdyoW1CuDgwxkD4"
  },
  "previewConfig": {
    "title": "ENS Lookup",
    "subtitle": "vitalik.eth",
    "displayFields": [
      "name",
      "address",
      "registrant",
      "expiry_date",
      "resolver",
      "content_hash"
    ]
  }
}
