{
  "id": "smartcar",
  "previewType": "card",
  "sampleResponse": {
    "vin": "1HGBH41JXMN109186",
    "make": "Honda",
    "model": "Civic",
    "year": 2022,
    "engine": "1.5L Turbo 4-cyl",
    "fuel_type": "Gasoline",
    "transmission": "CVT"
  },
  "previewConfig": {
    "title": "Smartcar",
    "subtitle": "Lock and unlock vehicles and get data like odometer reading and location. Works on most new cars",
    "displayFields": [
      "vin",
      "make",
      "model",
      "year",
      "engine",
      "fuel_type"
    ]
  }
}
