{
  "id": "wikipedia",
  "previewType": "card",
  "sampleResponse": {
    "title": "Aurora Borealis",
    "extract": "An aurora is a natural light display in Earth's sky, predominantly seen in high-latitude regions around the Arctic and Antarctic.",
    "description": "Natural light display in the sky",
    "lastEdited": "2026-01-14T08:22:00Z",
    "language": "English"
  },
  "previewConfig": {
    "title": "Aurora Borealis",
    "subtitle": "Wikipedia",
    "displayFields": ["title", "extract", "description", "lastEdited", "language"]
  }
}
